{"schema":{"vm":{"id":"vm","type":{"dataType":"reference","referenceType":"VC:VirtualMachine"},"label":"vm","constraints":{"required":false}},"name":{"id":"name","type":{"dataType":"string"},"label":"name","constraints":{"required":false}},"description":{"id":"description","type":{"dataType":"string"},"label":"description","constraints":{"required":false}},"expirationDate":{"id":"expirationDate","type":{"dataType":"dateTime"},"label":"expirationDate","constraints":{"required":false}}},"layout":{"pages":[{"id":"page_inx8xtjd","title":"General","sections":[{"id":"section_129meh0m","fields":[{"id":"vm","display":"valuePickerTree"}]},{"id":"section_5q2lnmn3","fields":[{"id":"name","display":"textField"}]},{"id":"section_68a9hf8y","fields":[{"id":"description","display":"textField"}]},{"id":"section_umojxe76","fields":[{"id":"expirationDate","display":"dateTime"}]}]}]},"itemId":""}